{
  "id": {
    "type": "Key",
    "used": false,
    "structured": "attribute"
  },
  "subject": {
    "type": "Text",
    "used": true,
    "structured": "attribute"
  },
  "description": {
    "type": "Text",
    "used": true,
    "structured": "attribute"
  },
  "textload": {
    "type": "Key",
    "used": false,
    "structured": "attribute"
  },
  "label_0": {
    "type": "Label",
    "used": true,
    "structured": "attribute"
  },
  "label_1": {
    "type": "Label",
    "used": true,
    "structured": "attribute"
  },
  "has_emoji": {
    "type": "Nominal",
    "used": false,
    "structured": "attribute"
  }
}